LICENSE
MANIFEST.in
README.md
pyproject.toml
setup.py
fim_python.egg-info/PKG-INFO
fim_python.egg-info/SOURCES.txt
fim_python.egg-info/dependency_links.txt
fim_python.egg-info/requires.txt
fim_python.egg-info/top_level.txt
fimpy/__init__.py
fimpy/cupy_kernels.py
fimpy/fim_base.py
fimpy/fim_cupy.py
fimpy/fim_np.py
fimpy/solver.py
fimpy/fim_cutils/__init__.py
fimpy/fim_cutils/fim_cutils.cpp
fimpy/fim_cutils/fim_cutils.pyx
fimpy/utils/__init__.py
fimpy/utils/comp.py
fimpy/utils/tsitsiklis.py
fimpy/utils/cython/__init__.py
fimpy/utils/cython/comp.cpp
fimpy/utils/cython/comp.pyx
tests/test_custom_kernels.py
tests/test_cython_methods.py
tests/test_fim_solvers.py