Metadata-Version: 2.1
Name: fim-python
Version: 1.2.2
Summary: This repository implements the Fast Iterative Method on tetrahedral domains and triangulated surfaces purely in python both for CPU (numpy) and GPU (cupy).
Home-page: https://github.com/thomgrand/fim-python
Author: Thomas Grandits
Author-email: tomdev@gmx.net
License: AGPL
Classifier: Programming Language :: Python :: 3
Classifier: Programming Language :: Cython
Classifier: Topic :: Scientific/Engineering :: Mathematics
Classifier: Operating System :: POSIX :: Linux
Classifier: Operating System :: Microsoft :: Windows
Classifier: Environment :: GPU :: NVIDIA CUDA
Classifier: License :: OSI Approved :: GNU Affero General Public License v3
Requires-Python: >=3.6
License-File: LICENSE
Requires-Dist: numpy
Requires-Dist: Cython>=0.29.22
Provides-Extra: gpu
Requires-Dist: cupy>=9.0; extra == "gpu"
Provides-Extra: tests
Requires-Dist: scipy; extra == "tests"
Requires-Dist: pytest; extra == "tests"
Requires-Dist: pytest-cov; extra == "tests"
Requires-Dist: matplotlib; extra == "tests"
Requires-Dist: pandas; extra == "tests"
Requires-Dist: ipython; extra == "tests"
Provides-Extra: docs
Requires-Dist: sphinx; extra == "docs"
Requires-Dist: pydata_sphinx_theme; extra == "docs"
Requires-Dist: pandas; extra == "docs"
Requires-Dist: ipython; extra == "docs"
